flammenwerfer/__init__.py
flammenwerfer/hash/fnv.py
flammenwerfer/localization.py
flammenwerfer/py.typed
flammenwerfer-0.1.9.dist-info/LICENSE
flammenwerfer-0.1.9.dist-info/METADATA
flammenwerfer-0.1.9.dist-info/WHEEL
flammenwerfer-0.1.9.dist-info/RECORD
