Metadata-Version: 2.1
Name: flammenwerfer
Version: 0.1.9
Summary: Python utility for processing Frostbite engine game files and interacting with the Frosty Editor.
Home-page: https://github.com/BF1CHS/flammenwerfer
Keywords: Frostbite,entertainment,reverse engineering,game development
Author: MaxMixAlex
Author-email: MaxMixAlex@protonmail.com
Requires-Python: >=3.8,<4.0
Classifier: Development Status :: 3 - Alpha
Classifier: Environment :: Console
Classifier: Intended Audience :: Developers
Classifier: Intended Audience :: End Users/Desktop
Classifier: Intended Audience :: Other Audience
Classifier: License :: OSI Approved :: GNU General Public License v3 (GPLv3)
Classifier: Operating System :: OS Independent
Classifier: Programming Language :: Python
Classifier: Programming Language :: Python :: 3
Classifier: Programming Language :: Python :: 3.8
Classifier: Programming Language :: Python :: 3.9
Classifier: Programming Language :: Python :: 3.10
Classifier: Programming Language :: Python :: 3.11
Classifier: Programming Language :: Python :: 3.12
Classifier: Topic :: Games/Entertainment
Project-URL: Repository, https://github.com/BF1CHS/flammenwerfer
